LICENSE
MANIFEST.in
README.md
setup.py
botgui/__init__.py
botgui/cript.py
botgui/exceptions.py
botgui/globals_gui.py
botgui/interface.py
botgui.egg-info/PKG-INFO
botgui.egg-info/SOURCES.txt
botgui.egg-info/dependency_links.txt
botgui.egg-info/requires.txt
botgui.egg-info/top_level.txt
botgui/assets/configuracoes.png
botgui/assets/customgui.png
botgui/assets/customgui2.png
botgui/assets/customgui3.png
botgui/assets/customgui4.png
botgui/assets/customgui5.png
botgui/assets/database.png
botgui/assets/home.png
botgui/assets/home2.png
botgui/assets/info.png
botgui/assets/options.png
botgui/assets/robo_hi.png
botgui/assets/robot.png
botgui/assets/warning.png