Metadata-Version: 2.1
Name: botgui
Version: 0.1.3
Summary: Class to build custom UI for bot processes
Home-page: https://github.com/botlorien/botgui
Author: Ben-Hur P. B. Santos
Author-email: botlorien@gmail.com
Classifier: Programming Language :: Python :: 3
Classifier: License :: OSI Approved :: MIT License
Classifier: Operating System :: OS Independent
Requires-Python: >=3.10
License-File: LICENSE
Requires-Dist: customtkinter
Requires-Dist: pillow
Requires-Dist: tkcalendar
Requires-Dist: python-dotenv
Requires-Dist: cryptography
